Workbook

Sheet 1. Executive Summary
B2: DCF Valuation Model
B3: Apple Inc. (NASDAQ: AAPL) — As of October 2026
B5: Case study for educational use. Not investment advice or a recommendation to buy, sell, or hold any security. Projections are illustrative.
B8: COMPANY OVERVIEW
B9: Company | C9: Apple Inc.
B10: Ticker | C10: NASDAQ: AAPL
B11: Sector | C11: Information Technology
B12: Industry | C12: Consumer Electronics / Technology
B13: Fiscal Year End | C13: September (FY2025 ended Sep 27, 2025)
B14: Current Price | C14: $330.00
B15: Market Capitalization | C15: $4,874B
B16: Shares Outstanding | C16: 14,770M
B17: Dividend Yield | C17: ~0.5%
B20: VALUATION SUMMARY
B21: Enterprise Value | C21: Equity Value | D21: Implied Share Price | E21: Current Share Price | F21: Upside/(Downside) | G21: Recommendation
B22: ='7. Valuation Summary'!E20 -> 2098714.1 | C22: ='7. Valuation Summary'!E22 -> 2041034.1 | D22: ='7. Valuation Summary'!E24 -> 138.18782 | E22: 330 | F22: ='7. Valuation Summary'!E26 -> -0.58124902 | G22: ='7. Valuation Summary'!E27 -> SELL
B24: KEY ASSUMPTIONS
B25: Assumption | C25: Value | D25: Source/Rationale | G25: Notes
B26: Revenue growth (avg 5yr) | C26: ='3. Assumptions'!C12 -> 0.051859895 | D26: Blended growth rate | G26: Gradual deceleration
B27: Terminal gross margin | C27: ='3. Assumptions'!C20 -> 0.031 | D27: Services mix shift | G27: 48.5% by FY2030
B28: WACC | C28: ='6. WACC'!J1 -> 0.093715428 | D28: CAPM + market weights | G28: Calculated from inputs
B29: Terminal growth rate | C29: ='3. Assumptions'!C30 -> 0 | D29: Long-term GDP growth | G29: Conservative
B30: Effective tax rate | C30: ='3. Assumptions'!C24 -> 0 | D30: Statutory rate | G30: Post-tax reform

Sheet 2. Historical Financials
B2: Historical Financial Summary
B3: Apple Inc. — FY2021-FY2025 (in millions USD)
B5: INCOME STATEMENT
B6: Metric ($M) | C6: FY2021 | D6: FY2022 | E6: FY2023 | F6: FY2024 | G6: FY2025
B7: Revenue | C7: 365817 | D7: 394328 | E7: 383285 | F7: 391035 | G7: 416161
B8: Cost of Revenue (COGS) | C8: 212981 | D8: 223546 | E8: 214137 | F8: 210352 | G8: 220960
B9: Gross Profit | C9: 152836 | D9: 170782 | E9: 169148 | F9: 180683 | G9: 195201
B10: R&D Expenses | C10: 21914 | D10: 26251 | E10: 29915 | F10: 31370 | G10: 34550
B11: SG&A Expenses | C11: 21973 | D11: 25094 | E11: 24932 | F11: 26097 | G11: 27601
B12: Total Operating Expenses | C12: 43887 | D12: 51345 | E12: 54847 | F12: 57467 | G12: 62151
B13: Operating Income (EBIT) | C13: 108949 | D13: 119437 | E13: 114301 | F13: 123216 | G13: 133050
B14: Income Tax Expense | C14: 14527 | D14: 19300 | E14: 16741 | F14: 29749 | G14: 20719
B15: Net Income | C15: 94680 | D15: 99803 | E15: 96995 | F15: 93736 | G15: 112010
B17: KEY MARGINS & RATIOS
B18: Revenue Growth | D18: 0.078 | E18: -0.028 | F18: 0.02 | G18: 0.064
B19: Gross Margin | C19: 0.418 | D19: 0.433 | E19: 0.441 | F19: 0.462 | G19: 0.469
B20: R&D as % of Revenue | C20: 0.06 | D20: 0.067 | E20: 0.078 | F20: 0.08 | G20: 0.083
B21: SG&A as % of Revenue | C21: 0.06 | D21: 0.064 | E21: 0.065 | F21: 0.067 | G21: 0.066
B22: Operating Margin (EBIT) | C22: 0.298 | D22: 0.303 | E22: 0.298 | F22: 0.315 | G22: 0.32
B23: Effective Tax Rate | C23: 0.133 | D23: 0.162 | E23: 0.146 | F23: 0.241 | G23: 0.156
B24: Net Margin | C24: 0.259 | D24: 0.253 | E24: 0.253 | F24: 0.24 | G24: 0.269
B27: BALANCE SHEET & CASH FLOW
B28: Cash & Short-term Investments | C28: 62639 | D28: 48304 | E28: 61555 | F28: 65171 | G28: 54697
B29: Total Debt | C29: 136522 | D29: 132480 | E29: 123930 | F29: 119059 | G29: 112377
B30: Net Debt | C30: 73883 | D30: 84176 | E30: 62375 | F30: 53888 | G30: 57680
B31: Total Equity | C31: 63090 | D31: 50672 | E31: 62146 | F31: 56950 | G31: 73733
B32: Total Assets | C32: 351002 | D32: 352755 | E32: 352583 | F32: 364980 | G32: 359241
B33: Depreciation & Amortization | C33: 11284 | D33: 11104 | E33: 11519 | F33: 11445 | G33: 11698
B34: Capital Expenditure | C34: 9709 | D34: 10708 | E34: 10959 | F34: 9447 | G34: 12715
B35: Free Cash Flow | C35: 92953 | D35: 111443 | E35: 99584 | F35: 108807 | G35: 98767
B36: Diluted Shares Outstanding | C36: 16464 | D36: 16216 | E36: 15813 | F36: 15406 | G36: 15005
B39: Source: Apple Inc. FY2025 Form 10-K (SEC filing), StockAnalysis.com, Macrotrends.net

Sheet 3. Assumptions
B2: Valuation Assumptions
B3: All projection inputs — change yellow cells to update the entire model
B5: REVENUE GROWTH ASSUMPTIONS
B6: Fiscal Year | C6: Growth Rate
B7: FY2026E | C7: 0.08 | E7: iPhone 17 cycle, Services growth
B8: FY2027E | C8: 0.06 | E8: Continued Services momentum
B9: FY2028E | C9: 0.05 | E9: Maturing product cycle
B10: FY2029E | C10: 0.04 | E10: Gradual deceleration
B11: FY2030E | C11: 0.03 | E11: Approaching long-term growth
B12: 5-Year Average Growth (CAGR) | C12: =(PRODUCT(1+C7,1+C8,1+C9,1+C10,1+C11))^(1/5)-1 -> 0.051859895
B14: MARGIN ASSUMPTIONS (AS % OF REVENUE)
B15: Metric | C15: FY2025A | D15: FY2030E
B16: Gross Margin | C16: 0.469 | D16: 0.485 | E16: Services mix shift improves margin
B17: R&D as % of Revenue | C17: 0.083 | D17: 0.085 | E17: Continued AI/AR investment
B18: SG&A as % of Revenue | C18: 0.066 | D18: 0.064 | E18: Operating leverage
B19: D&A as % of Revenue | C19: 0.028 | D19: 0.03 | E19: Capex ramp for data centers
B20: Capex as % of Revenue | C20: 0.031 | D20: 0.035 | E20: Infrastructure investment
B22: Note: Margins for FY2026-FY2029 are linearly interpolated between FY2025A and FY2030E
B24: TAX & OTHER ASSUMPTIONS
B25: Assumption | C25: Value
B26: Effective Tax Rate | C26: 0.24 | E26: U.S. statutory rate post-TCJA
B27: Net Working Capital (% of Revenue) | C27: 0.02 | E27: Minimal WC needs (asset-light)
B28: Shares Outstanding (M) | C28: 14770 | E28: FY2025 diluted weighted average
B29: Current Share Price | C29: 330 | E29: As of October 1, 2026
B31: TERMINAL VALUE ASSUMPTIONS
B32: Assumption | C32: Value
B33: Terminal Growth Rate | C33: 0.03 | E33: Long-term U.S. GDP growth
B34: Terminal WACC | C34: =C30 -> 0 | E34: Same as projection period WACC
B35: Exit EV/EBITDA Multiple | C35: 18 | E35: Peer median for mature tech
B38: LEGEND
B39: Blue text on yellow fill | C39: Input assumption — change to update model
B40: Blue text on light fill | C40: Historical data input
B41: Black text | C41: Calculated formula
B42: Green text | C42: Direct link to another sheet

Sheet 4. Income Statement
B2: Income Statement Projections
B3: Apple Inc. — FY2025A through FY2030E (in millions USD)
B5: Income Statement ($M) | C5: FY2025A | D5: FY2026E | E5: FY2027E | F5: FY2028E | G5: FY2029E | H5: FY2030E
B7: Revenue | C7: ='2. Historical Financials'!G7 -> 416161 | D7: =C7*(1+'3. Assumptions'!C7) -> 449453.88 | E7: =D7*(1+'3. Assumptions'!C8) -> 476421.11 | F7: =E7*(1+'3. Assumptions'!C9) -> 500242.17 | G7: =F7*(1+'3. Assumptions'!C10) -> 520251.86 | H7: =G7*(1+'3. Assumptions'!C11) -> 535859.41
B8: Cost of Revenue (COGS) | C8: ='2. Historical Financials'!G8 -> 220960 | D8: =D7*(1-('3. Assumptions'!C16 + ('3. Assumptions'!D16 - '3. Assumptions'!C16) * 1/5)) -> 237221.76 | E8: =E7*(1-('3. Assumptions'!C16 + ('3. Assumptions'!D16 - '3. Assumptions'!C16) * 2/5)) -> 249930.52 | F8: =F7*(1-('3. Assumptions'!C16 + ('3. Assumptions'!D16 - '3. Assumptions'!C16) * 3/5)) -> 260826.27 | G8: =G7*(1-('3. Assumptions'!C16 + ('3. Assumptions'!D16 - '3. Assumptions'!C16) * 4/5)) -> 269594.51 | H8: =H7*(1-('3. Assumptions'!C16 + ('3. Assumptions'!D16 - '3. Assumptions'!C16) * 5/5)) -> 275967.6
B9: Gross Profit | C9: =C7-C8 -> 195201 | D9: =D7-D8 -> 212232.12 | E9: =E7-E8 -> 226490.6 | F9: =F7-F8 -> 239415.9 | G9: =G7-G8 -> 250657.34 | H9: =H7-H8 -> 259891.81
B10: R&D Expenses | C10: ='2. Historical Financials'!G9 -> 195201 | D10: =D7*('3. Assumptions'!C17 + ('3. Assumptions'!D17 - '3. Assumptions'!C17) * 1/5) -> 37484.454 | E10: =E7*('3. Assumptions'!C17 + ('3. Assumptions'!D17 - '3. Assumptions'!C17) * 2/5) -> 39924.089 | F10: =F7*('3. Assumptions'!C17 + ('3. Assumptions'!D17 - '3. Assumptions'!C17) * 3/5) -> 42120.391 | G10: =G7*('3. Assumptions'!C17 + ('3. Assumptions'!D17 - '3. Assumptions'!C17) * 4/5) -> 44013.307 | H10: =H7*('3. Assumptions'!C17 + ('3. Assumptions'!D17 - '3. Assumptions'!C17) * 5/5) -> 45548.05
B11: SG&A Expenses | C11: ='2. Historical Financials'!G10 -> 34550 | D11: =D7*('3. Assumptions'!C18 + ('3. Assumptions'!D18 - '3. Assumptions'!C18) * 1/5) -> 29484.175 | E11: =E7*('3. Assumptions'!C18 + ('3. Assumptions'!D18 - '3. Assumptions'!C18) * 2/5) -> 31062.657 | F11: =F7*('3. Assumptions'!C18 + ('3. Assumptions'!D18 - '3. Assumptions'!C18) * 3/5) -> 32415.693 | G11: =G7*('3. Assumptions'!C18 + ('3. Assumptions'!D18 - '3. Assumptions'!C18) * 4/5) -> 33504.219 | H11: =H7*('3. Assumptions'!C18 + ('3. Assumptions'!D18 - '3. Assumptions'!C18) * 5/5) -> 34295.002
B12: D&A | C12: ='2. Historical Financials'!G33 -> 11698 | D12: =D7*('3. Assumptions'!C19 + ('3. Assumptions'!D19 - '3. Assumptions'!C19) * 1/5) -> 12764.49 | E12: =E7*('3. Assumptions'!C19 + ('3. Assumptions'!D19 - '3. Assumptions'!C19) * 2/5) -> 13720.928 | F12: =F7*('3. Assumptions'!C19 + ('3. Assumptions'!D19 - '3. Assumptions'!C19) * 3/5) -> 14607.071 | G12: =G7*('3. Assumptions'!C19 + ('3. Assumptions'!D19 - '3. Assumptions'!C19) * 4/5) -> 15399.455 | H12: =H7*('3. Assumptions'!C19 + ('3. Assumptions'!D19 - '3. Assumptions'!C19) * 5/5) -> 16075.782
B13: Capex | C13: ='2. Historical Financials'!G34 -> 12715 | D13: =D7*('3. Assumptions'!C20 + ('3. Assumptions'!D20 - '3. Assumptions'!C20) * 1/5) -> 14292.633 | E13: =E7*('3. Assumptions'!C20 + ('3. Assumptions'!D20 - '3. Assumptions'!C20) * 2/5) -> 15531.328 | F13: =F7*('3. Assumptions'!C20 + ('3. Assumptions'!D20 - '3. Assumptions'!C20) * 3/5) -> 16708.088 | G13: =G7*('3. Assumptions'!C20 + ('3. Assumptions'!D20 - '3. Assumptions'!C20) * 4/5) -> 17792.613 | H13: =H7*('3. Assumptions'!C20 + ('3. Assumptions'!D20 - '3. Assumptions'!C20) * 5/5) -> 18755.079
B15: Operating Income (EBIT) | C15: =C9-C10-C11 -> -34550 | D15: =D9-D10-D11 -> 145263.49 | E15: =E9-E10-E11 -> 155503.85 | F15: =F9-F10-F11 -> 164879.82 | G15: =G9-G10-G11 -> 173139.82 | H15: =H9-H10-H11 -> 180048.76
B16: EBITDA | C16: =C15+C12 -> -22852 | D16: =D15+D12 -> 158027.98 | E16: =E15+E12 -> 169224.78 | F16: =F15+F12 -> 179486.89 | G16: =G15+G12 -> 188539.27 | H16: =H15+H12 -> 196124.54
B18: Income Tax Expense | C18: ='2. Historical Financials'!G13 -> 133050 | D18: =D15*'3. Assumptions'!C26 -> 34863.239 | E18: =E15*'3. Assumptions'!C26 -> 37320.924 | F18: =F15*'3. Assumptions'!C26 -> 39571.156 | G18: =G15*'3. Assumptions'!C26 -> 41553.556 | H18: =H15*'3. Assumptions'!C26 -> 43211.703
B19: Net Income | C19: =C15-C18 -> -167600 | D19: =D15-D18 -> 110400.26 | E19: =E15-E18 -> 118182.93 | F19: =F15-F18 -> 125308.66 | G19: =G15-G18 -> 131586.26 | H19: =H15-H18 -> 136837.06
B21: KEY MARGINS
B22: Margin | C22: FY2025A | D22: FY2026E | E22: FY2027E | F22: FY2028E | G22: FY2029E | H22: FY2030E
B23: Gross Margin | C23: =C9/C7 -> 0.46905164 | D23: =D9/D7 -> 0.4722 | E23: =E9/E7 -> 0.4754 | F23: =F9/F7 -> 0.4786 | G23: =G9/G7 -> 0.4818 | H23: =H9/H7 -> 0.485
B24: R&D Margin | C24: =C10/C7 -> 0.46905164 | D24: =D10/D7 -> 0.0834 | E24: =E10/E7 -> 0.0838 | F24: =F10/F7 -> 0.0842 | G24: =G10/G7 -> 0.0846 | H24: =H10/H7 -> 0.085
B25: SG&A Margin | C25: =C11/C7 -> 0.083020754 | D25: =D11/D7 -> 0.0656 | E25: =E11/E7 -> 0.0652 | F25: =F11/F7 -> 0.0648 | G25: =G11/G7 -> 0.0644 | H25: =H11/H7 -> 0.064
B26: Operating Margin (EBIT) | C26: =C15/C7 -> -0.083020754 | D26: =D15/D7 -> 0.3232 | E26: =E15/E7 -> 0.3264 | F26: =F15/F7 -> 0.3296 | G26: =G15/G7 -> 0.3328 | H26: =H15/H7 -> 0.336
B27: EBITDA Margin | C27: =C16/C7 -> -0.054911441 | D27: =D16/D7 -> 0.3516 | E27: =E16/E7 -> 0.3552 | F27: =F16/F7 -> 0.3588 | G27: =G16/G7 -> 0.3624 | H27: =H16/H7 -> 0.366
B28: Net Margin | C28: =C19/C7 -> -0.40272875 | D28: =D19/D7 -> 0.245632 | E28: =E19/E7 -> 0.248064 | F28: =F19/F7 -> 0.250496 | G28: =G19/G7 -> 0.252928 | H28: =H19/H7 -> 0.25536

Sheet 5. Free Cash Flow
B2: Free Cash Flow Projections
B3: Unlevered Free Cash Flow (FCFF) — FY2025A through FY2030E
B5: Free Cash Flow ($M) | C5: FY2025A | D5: FY2026E | E5: FY2027E | F5: FY2028E | G5: FY2029E | H5: FY2030E
B7: EBIT (Operating Income) | C7: ='4. Income Statement'!C15 -> -34550 | D7: ='4. Income Statement'!D15 -> 145263.49 | E7: ='4. Income Statement'!E15 -> 155503.85 | F7: ='4. Income Statement'!F15 -> 164879.82 | G7: ='4. Income Statement'!G15 -> 173139.82 | H7: ='4. Income Statement'!H15 -> 180048.76
B8: Tax Rate | C8: ='3. Assumptions'!$C$26 -> 0.24 | D8: ='3. Assumptions'!$C$26 -> 0.24 | E8: ='3. Assumptions'!$C$26 -> 0.24 | F8: ='3. Assumptions'!$C$26 -> 0.24 | G8: ='3. Assumptions'!$C$26 -> 0.24 | H8: ='3. Assumptions'!$C$26 -> 0.24
B9: NOPAT [EBIT x (1 - Tax Rate)] | C9: =C7*(1-C8) -> -26258 | D9: =D7*(1-D8) -> 110400.26 | E9: =E7*(1-E8) -> 118182.93 | F9: =F7*(1-F8) -> 125308.66 | G9: =G7*(1-G8) -> 131586.26 | H9: =H7*(1-H8) -> 136837.06
B10: Depreciation & Amortization | C10: ='4. Income Statement'!C12 -> 11698 | D10: ='4. Income Statement'!D12 -> 12764.49 | E10: ='4. Income Statement'!E12 -> 13720.928 | F10: ='4. Income Statement'!F12 -> 14607.071 | G10: ='4. Income Statement'!G12 -> 15399.455 | H10: ='4. Income Statement'!H12 -> 16075.782
B11: Capital Expenditure | C11: ='4. Income Statement'!C13 -> 12715 | D11: ='4. Income Statement'!D13 -> 14292.633 | E11: ='4. Income Statement'!E13 -> 15531.328 | F11: ='4. Income Statement'!F13 -> 16708.088 | G11: ='4. Income Statement'!G13 -> 17792.613 | H11: ='4. Income Statement'!H13 -> 18755.079
B12: Change in Net Working Capital | C12: 0 | D12: =(D7-'4. Income Statement'!C7)*'3. Assumptions'!$C$27 -> -5417.9501 | E12: =(E7-'4. Income Statement'!D7)*'3. Assumptions'!$C$27 -> -5879.0006 | F12: =(F7-'4. Income Statement'!E7)*'3. Assumptions'!$C$27 -> -6230.8259 | G12: =(G7-'4. Income Statement'!F7)*'3. Assumptions'!$C$27 -> -6542.047 | H12: =(H7-'4. Income Statement'!G7)*'3. Assumptions'!$C$27 -> -6804.0619
B14: Unlevered Free Cash Flow (FCFF) | C14: =C9+C10-C11-C12 -> -27275 | D14: =D9+D10-D11-D12 -> 114290.06 | E14: =E9+E10-E11-E12 -> 122251.53 | F14: =F9+F10-F11-F12 -> 129438.47 | G14: =G9+G10-G11-G12 -> 135735.15 | H14: =H9+H10-H11-H12 -> 140961.82
B16: FCFF Margin | C16: =C14/'4. Income Statement'!C7 -> -0.065539539 | D16: =D14/'4. Income Statement'!D7 -> 0.25428652 | E16: =E14/'4. Income Statement'!E7 -> 0.25660392 | F16: =F14/'4. Income Statement'!F7 -> 0.25875162 | G16: =G14/'4. Income Statement'!G7 -> 0.26090277 | H16: =H14/'4. Income Statement'!H7 -> 0.26305748
B18: DISCOUNTING
B19: Item | C19: FY2025A | D19: FY2026E | E19: FY2027E | F19: FY2028E | G19: FY2029E | H19: FY2030E
B20: WACC | C20: ='6. WACC'!$E$18 -> 0 | D20: ='6. WACC'!$E$18 -> 0 | E20: ='6. WACC'!$E$18 -> 0 | F20: ='6. WACC'!$E$18 -> 0 | G20: ='6. WACC'!$E$18 -> 0 | H20: ='6. WACC'!$E$18 -> 0
B21: Period (n) | C21: 0 | D21: 1 | E21: 2 | F21: 3 | G21: 4 | H21: 5
B22: Discount Factor [1/(1+WACC)^n] | C22: 1 | D22: =1/(1+D20)^D21 -> 1 | E22: =1/(1+E20)^E21 -> 1 | F22: =1/(1+F20)^F21 -> 1 | G22: =1/(1+G20)^G21 -> 1 | H22: =1/(1+H20)^H21 -> 1
B24: PV of FCFF | C24: 0 | D24: =D14*D22 -> 114290.06 | E24: =E14*E22 -> 122251.53 | F24: =F14*F22 -> 129438.47 | G24: =G14*G22 -> 135735.15 | H24: =H14*H22 -> 140961.82
B26: Sum of PV (FCFF, FY2026-FY2030) | F26: =SUM(D24:H24) -> 642677.03

Sheet 6. WACC
J1: =E26 -> 0.093715428
B2: Weighted Average Cost of Capital (WACC)
B3: CAPM-based cost of equity + market-value capital weights
B5: COST OF EQUITY (CAPM)
B6: Component | C6: Value | D6: Source
B7: Risk-Free Rate (10Y Treasury) | C7: 0.041 | D7: U.S. 10Y Treasury yield (Oct 2026)
B8: Equity Risk Premium | C8: 0.045 | D8: Long-term ERP estimate (Damodaran)
B9: Beta | C9: 1.2 | D9: 5-year monthly regression vs S&P 500
B10: Cost of Equity [Rf + Beta x ERP] | C10: =C7+C9*C8 -> 0.095 | E10: Result: ~9.5%
B12: COST OF DEBT
B13: Component | C13: Value | D13: Source
B14: Pre-Tax Cost of Debt | C14: 0.05 | D14: Weighted avg coupon on outstanding debt
B15: Tax Rate | C15: ='3. Assumptions'!C26 -> 0.24 | D15: Statutory tax rate
B16: After-Tax Cost of Debt [Kd x (1 - Tax)] | C16: =C14*(1-C15) -> 0.038
B18: CAPITAL STRUCTURE (MARKET VALUES)
B19: WACC CALCULATION
B20: Component | C20: Value ($M) | D20: Weight | E20: Cost | F20: Contribution
B21: Market Value of Equity (E) | C21: ='3. Assumptions'!C28*'3. Assumptions'!C29 -> 4874100 | D21: =C21/$C$23 -> 0.97746365 | E21: =C10 -> 0.095 | F21: =D21*E21 -> 0.092859047
B22: Market Value of Debt (D) | C22: ='2. Historical Financials'!G29 -> 112377 | D22: =C22/$C$23 -> 0.022536352 | E22: =C16 -> 0.038 | F22: =D22*E22 -> 0.00085638137
B23: Total Capital (V = E + D) | C23: =C21+C22 -> 4986477 | D23: =D21+D22 -> 1
B26: WACC | E26: =F21+F22 -> 0.093715428

Sheet 7. Valuation Summary
B2: Valuation Summary
B3: Enterprise value, equity value, and implied share price
B5: DCF VALUATION (GORDON GROWTH)
B6: Component | C6: Value ($M) | D6: Notes
B7: PV of Explicit FCFF (FY2026-FY2030) | C7: ='5. Free Cash Flow'!F26 -> 642677.03 | D7: Sum of discounted unlevered FCF
B9: TERMINAL VALUE CALCULATION
B10: FY2030E FCFF | C10: ='5. Free Cash Flow'!H14 -> 140961.82 | D10: Final year unlevered FCF
B11: Terminal Growth Rate | C11: ='3. Assumptions'!C33 -> 0.03 | D11: Long-term GDP growth
B12: Terminal WACC | C12: ='6. WACC'!J1 -> 0.093715428 | D12: Same as projection WACC
B13: Terminal Value [FCFF x (1+g) / (WACC - g)] | C13: =C10*(1+C11)/(C12-C11) -> 2278736.6 | D13: Gordon Growth Model
B14: PV of Terminal Value | C14: =C13/(1+C12)^5 -> 1456037.1 | D14: Discounted at WACC for 5 years
B16: VALUATION SUMMARY
B17: PV of Explicit FCFF | C17: =C7 -> 642677.03
B18: PV of Terminal Value | C18: =C14 -> 1456037.1
B19: Terminal Value % of EV | C19: =C18/E20 -> 0.69377581
B20: Enterprise Value | E20: =C17+C18 -> 2098714.1
B22: Less: Net Debt | C22: ='2. Historical Financials'!G30 -> 57680 | E22: =E20-C22 -> 2041034.1
B24: Implied Share Price | E24: =E22/'3. Assumptions'!C28 -> 138.18782
B26: Upside/(Downside) vs Current | E26: =E24/'3. Assumptions'!C29-1 -> -0.58124902
B27: Recommendation | E27: =IF(E26>0.15,"BUY",IF(E26>-0.15,"HOLD","SELL")) -> SELL

Sheet 8. Sensitivity
B2: Sensitivity Analysis
B3: Implied share price under varying WACC and terminal growth rates
B5: WACC | C5: 0.02 | D5: 0.025 | E5: 0.03 | F5: 0.035 | G5: 0.04
B6: 0.08 | C6: =('5. Free Cash Flow'!D14/(1+B6)^1+'5. Free Cash Flow'!E14/(1+B6)^2+'5. Free Cash Flow'!F14/(1+B6)^3+'5. Free Cash Flow'!G14/(1+B6)^4+'5. Free Cash Flow'!H14/(1+B6)^5+'5. Free Cash Flow'!H14*(1+C$5)/(B6-C$5)/(1+B6)^5-'2. Historical Financials'!G30)/'3. Assumptions'!C28 -> 140.98371 | D6: =('5. Free Cash Flow'!D14/(1+B6)^1+'5. Free Cash Flow'!E14/(1+B6)^2+'5. Free Cash Flow'!F14/(1+B6)^3+'5. Free Cash Flow'!G14/(1+B6)^4+'5. Free Cash Flow'!H14/(1+B6)^5+'5. Free Cash Flow'!H14*(1+D$5)/(B6-D$5)/(1+B6)^5-'2. Historical Financials'!G30)/'3. Assumptions'!C28 -> 151.61246 | E6: =('5. Free Cash Flow'!D14/(1+B6)^1+'5. Free Cash Flow'!E14/(1+B6)^2+'5. Free Cash Flow'!F14/(1+B6)^3+'5. Free Cash Flow'!G14/(1+B6)^4+'5. Free Cash Flow'!H14/(1+B6)^5+'5. Free Cash Flow'!H14*(1+E$5)/(B6-E$5)/(1+B6)^5-'2. Historical Financials'!G30)/'3. Assumptions'!C28 -> 164.36695 | F6: =('5. Free Cash Flow'!D14/(1+B6)^1+'5. Free Cash Flow'!E14/(1+B6)^2+'5. Free Cash Flow'!F14/(1+B6)^3+'5. Free Cash Flow'!G14/(1+B6)^4+'5. Free Cash Flow'!H14/(1+B6)^5+'5. Free Cash Flow'!H14*(1+F$5)/(B6-F$5)/(1+B6)^5-'2. Historical Financials'!G30)/'3. Assumptions'!C28 -> 179.95578 | G6: =('5. Free Cash Flow'!D14/(1+B6)^1+'5. Free Cash Flow'!E14/(1+B6)^2+'5. Free Cash Flow'!F14/(1+B6)^3+'5. Free Cash Flow'!G14/(1+B6)^4+'5. Free Cash Flow'!H14/(1+B6)^5+'5. Free Cash Flow'!H14*(1+G$5)/(B6-G$5)/(1+B6)^5-'2. Historical Financials'!G30)/'3. Assumptions'!C28 -> 199.44182
B7: 0.085 | C7: =('5. Free Cash Flow'!D14/(1+B7)^1+'5. Free Cash Flow'!E14/(1+B7)^2+'5. Free Cash Flow'!F14/(1+B7)^3+'5. Free Cash Flow'!G14/(1+B7)^4+'5. Free Cash Flow'!H14/(1+B7)^5+'5. Free Cash Flow'!H14*(1+C$5)/(B7-C$5)/(1+B7)^5-'2. Historical Financials'!G30)/'3. Assumptions'!C28 -> 129.69685 | D7: =('5. Free Cash Flow'!D14/(1+B7)^1+'5. Free Cash Flow'!E14/(1+B7)^2+'5. Free Cash Flow'!F14/(1+B7)^3+'5. Free Cash Flow'!G14/(1+B7)^4+'5. Free Cash Flow'!H14/(1+B7)^5+'5. Free Cash Flow'!H14*(1+D$5)/(B7-D$5)/(1+B7)^5-'2. Historical Financials'!G30)/'3. Assumptions'!C28 -> 138.52576 | E7: =('5. Free Cash Flow'!D14/(1+B7)^1+'5. Free Cash Flow'!E14/(1+B7)^2+'5. Free Cash Flow'!F14/(1+B7)^3+'5. Free Cash Flow'!G14/(1+B7)^4+'5. Free Cash Flow'!H14/(1+B7)^5+'5. Free Cash Flow'!H14*(1+E$5)/(B7-E$5)/(1+B7)^5-'2. Historical Financials'!G30)/'3. Assumptions'!C28 -> 148.95994 | F7: =('5. Free Cash Flow'!D14/(1+B7)^1+'5. Free Cash Flow'!E14/(1+B7)^2+'5. Free Cash Flow'!F14/(1+B7)^3+'5. Free Cash Flow'!G14/(1+B7)^4+'5. Free Cash Flow'!H14/(1+B7)^5+'5. Free Cash Flow'!H14*(1+F$5)/(B7-F$5)/(1+B7)^5-'2. Historical Financials'!G30)/'3. Assumptions'!C28 -> 161.48095 | G7: =('5. Free Cash Flow'!D14/(1+B7)^1+'5. Free Cash Flow'!E14/(1+B7)^2+'5. Free Cash Flow'!F14/(1+B7)^3+'5. Free Cash Flow'!G14/(1+B7)^4+'5. Free Cash Flow'!H14/(1+B7)^5+'5. Free Cash Flow'!H14*(1+G$5)/(B7-G$5)/(1+B7)^5-'2. Historical Financials'!G30)/'3. Assumptions'!C28 -> 176.78441
B8: 0.09 | C8: =('5. Free Cash Flow'!D14/(1+B8)^1+'5. Free Cash Flow'!E14/(1+B8)^2+'5. Free Cash Flow'!F14/(1+B8)^3+'5. Free Cash Flow'!G14/(1+B8)^4+'5. Free Cash Flow'!H14/(1+B8)^5+'5. Free Cash Flow'!H14*(1+C$5)/(B8-C$5)/(1+B8)^5-'2. Historical Financials'!G30)/'3. Assumptions'!C28 -> 120.02456 | D8: =('5. Free Cash Flow'!D14/(1+B8)^1+'5. Free Cash Flow'!E14/(1+B8)^2+'5. Free Cash Flow'!F14/(1+B8)^3+'5. Free Cash Flow'!G14/(1+B8)^4+'5. Free Cash Flow'!H14/(1+B8)^5+'5. Free Cash Flow'!H14*(1+D$5)/(B8-D$5)/(1+B8)^5-'2. Historical Financials'!G30)/'3. Assumptions'!C28 -> 127.4543 | E8: =('5. Free Cash Flow'!D14/(1+B8)^1+'5. Free Cash Flow'!E14/(1+B8)^2+'5. Free Cash Flow'!F14/(1+B8)^3+'5. Free Cash Flow'!G14/(1+B8)^4+'5. Free Cash Flow'!H14/(1+B8)^5+'5. Free Cash Flow'!H14*(1+E$5)/(B8-E$5)/(1+B8)^5-'2. Historical Financials'!G30)/'3. Assumptions'!C28 -> 136.12233 | F8: =('5. Free Cash Flow'!D14/(1+B8)^1+'5. Free Cash Flow'!E14/(1+B8)^2+'5. Free Cash Flow'!F14/(1+B8)^3+'5. Free Cash Flow'!G14/(1+B8)^4+'5. Free Cash Flow'!H14/(1+B8)^5+'5. Free Cash Flow'!H14*(1+F$5)/(B8-F$5)/(1+B8)^5-'2. Historical Financials'!G30)/'3. Assumptions'!C28 -> 146.36637 | G8: =('5. Free Cash Flow'!D14/(1+B8)^1+'5. Free Cash Flow'!E14/(1+B8)^2+'5. Free Cash Flow'!F14/(1+B8)^3+'5. Free Cash Flow'!G14/(1+B8)^4+'5. Free Cash Flow'!H14/(1+B8)^5+'5. Free Cash Flow'!H14*(1+G$5)/(B8-G$5)/(1+B8)^5-'2. Historical Financials'!G30)/'3. Assumptions'!C28 -> 158.65921
B9: 0.095 | C9: =('5. Free Cash Flow'!D14/(1+B9)^1+'5. Free Cash Flow'!E14/(1+B9)^2+'5. Free Cash Flow'!F14/(1+B9)^3+'5. Free Cash Flow'!G14/(1+B9)^4+'5. Free Cash Flow'!H14/(1+B9)^5+'5. Free Cash Flow'!H14*(1+C$5)/(B9-C$5)/(1+B9)^5-'2. Historical Financials'!G30)/'3. Assumptions'!C28 -> 111.6439 | D9: =('5. Free Cash Flow'!D14/(1+B9)^1+'5. Free Cash Flow'!E14/(1+B9)^2+'5. Free Cash Flow'!F14/(1+B9)^3+'5. Free Cash Flow'!G14/(1+B9)^4+'5. Free Cash Flow'!H14/(1+B9)^5+'5. Free Cash Flow'!H14*(1+D$5)/(B9-D$5)/(1+B9)^5-'2. Historical Financials'!G30)/'3. Assumptions'!C28 -> 117.9662 | E9: =('5. Free Cash Flow'!D14/(1+B9)^1+'5. Free Cash Flow'!E14/(1+B9)^2+'5. Free Cash Flow'!F14/(1+B9)^3+'5. Free Cash Flow'!G14/(1+B9)^4+'5. Free Cash Flow'!H14/(1+B9)^5+'5. Free Cash Flow'!H14*(1+E$5)/(B9-E$5)/(1+B9)^5-'2. Historical Financials'!G30)/'3. Assumptions'!C28 -> 125.26117 | F9: =('5. Free Cash Flow'!D14/(1+B9)^1+'5. Free Cash Flow'!E14/(1+B9)^2+'5. Free Cash Flow'!F14/(1+B9)^3+'5. Free Cash Flow'!G14/(1+B9)^4+'5. Free Cash Flow'!H14/(1+B9)^5+'5. Free Cash Flow'!H14*(1+F$5)/(B9-F$5)/(1+B9)^5-'2. Historical Financials'!G30)/'3. Assumptions'!C28 -> 133.77196 | G9: =('5. Free Cash Flow'!D14/(1+B9)^1+'5. Free Cash Flow'!E14/(1+B9)^2+'5. Free Cash Flow'!F14/(1+B9)^3+'5. Free Cash Flow'!G14/(1+B9)^4+'5. Free Cash Flow'!H14/(1+B9)^5+'5. Free Cash Flow'!H14*(1+G$5)/(B9-G$5)/(1+B9)^5-'2. Historical Financials'!G30)/'3. Assumptions'!C28 -> 143.83017
B10: 0.1 | C10: =('5. Free Cash Flow'!D14/(1+B10)^1+'5. Free Cash Flow'!E14/(1+B10)^2+'5. Free Cash Flow'!F14/(1+B10)^3+'5. Free Cash Flow'!G14/(1+B10)^4+'5. Free Cash Flow'!H14/(1+B10)^5+'5. Free Cash Flow'!H14*(1+C$5)/(B10-C$5)/(1+B10)^5-'2. Historical Financials'!G30)/'3. Assumptions'!C28 -> 104.31264 | D10: =('5. Free Cash Flow'!D14/(1+B10)^1+'5. Free Cash Flow'!E14/(1+B10)^2+'5. Free Cash Flow'!F14/(1+B10)^3+'5. Free Cash Flow'!G14/(1+B10)^4+'5. Free Cash Flow'!H14/(1+B10)^5+'5. Free Cash Flow'!H14*(1+D$5)/(B10-D$5)/(1+B10)^5-'2. Historical Financials'!G30)/'3. Assumptions'!C28 -> 109.74475 | E10: =('5. Free Cash Flow'!D14/(1+B10)^1+'5. Free Cash Flow'!E14/(1+B10)^2+'5. Free Cash Flow'!F14/(1+B10)^3+'5. Free Cash Flow'!G14/(1+B10)^4+'5. Free Cash Flow'!H14/(1+B10)^5+'5. Free Cash Flow'!H14*(1+E$5)/(B10-E$5)/(1+B10)^5-'2. Historical Financials'!G30)/'3. Assumptions'!C28 -> 115.95288 | F10: =('5. Free Cash Flow'!D14/(1+B10)^1+'5. Free Cash Flow'!E14/(1+B10)^2+'5. Free Cash Flow'!F14/(1+B10)^3+'5. Free Cash Flow'!G14/(1+B10)^4+'5. Free Cash Flow'!H14/(1+B10)^5+'5. Free Cash Flow'!H14*(1+F$5)/(B10-F$5)/(1+B10)^5-'2. Historical Financials'!G30)/'3. Assumptions'!C28 -> 123.11611 | G10: =('5. Free Cash Flow'!D14/(1+B10)^1+'5. Free Cash Flow'!E14/(1+B10)^2+'5. Free Cash Flow'!F14/(1+B10)^3+'5. Free Cash Flow'!G14/(1+B10)^4+'5. Free Cash Flow'!H14/(1+B10)^5+'5. Free Cash Flow'!H14*(1+G$5)/(B10-G$5)/(1+B10)^5-'2. Historical Financials'!G30)/'3. Assumptions'!C28 -> 131.47322
B11: 0.105 | C11: =('5. Free Cash Flow'!D14/(1+B11)^1+'5. Free Cash Flow'!E14/(1+B11)^2+'5. Free Cash Flow'!F14/(1+B11)^3+'5. Free Cash Flow'!G14/(1+B11)^4+'5. Free Cash Flow'!H14/(1+B11)^5+'5. Free Cash Flow'!H14*(1+C$5)/(B11-C$5)/(1+B11)^5-'2. Historical Financials'!G30)/'3. Assumptions'!C28 -> 97.845545 | D11: =('5. Free Cash Flow'!D14/(1+B11)^1+'5. Free Cash Flow'!E14/(1+B11)^2+'5. Free Cash Flow'!F14/(1+B11)^3+'5. Free Cash Flow'!G14/(1+B11)^4+'5. Free Cash Flow'!H14/(1+B11)^5+'5. Free Cash Flow'!H14*(1+D$5)/(B11-D$5)/(1+B11)^5-'2. Historical Financials'!G30)/'3. Assumptions'!C28 -> 102.55242 | E11: =('5. Free Cash Flow'!D14/(1+B11)^1+'5. Free Cash Flow'!E14/(1+B11)^2+'5. Free Cash Flow'!F14/(1+B11)^3+'5. Free Cash Flow'!G14/(1+B11)^4+'5. Free Cash Flow'!H14/(1+B11)^5+'5. Free Cash Flow'!H14*(1+E$5)/(B11-E$5)/(1+B11)^5-'2. Historical Financials'!G30)/'3. Assumptions'!C28 -> 107.88689 | F11: =('5. Free Cash Flow'!D14/(1+B11)^1+'5. Free Cash Flow'!E14/(1+B11)^2+'5. Free Cash Flow'!F14/(1+B11)^3+'5. Free Cash Flow'!G14/(1+B11)^4+'5. Free Cash Flow'!H14/(1+B11)^5+'5. Free Cash Flow'!H14*(1+F$5)/(B11-F$5)/(1+B11)^5-'2. Historical Financials'!G30)/'3. Assumptions'!C28 -> 113.98341 | G11: =('5. Free Cash Flow'!D14/(1+B11)^1+'5. Free Cash Flow'!E14/(1+B11)^2+'5. Free Cash Flow'!F14/(1+B11)^3+'5. Free Cash Flow'!G14/(1+B11)^4+'5. Free Cash Flow'!H14/(1+B11)^5+'5. Free Cash Flow'!H14*(1+G$5)/(B11-G$5)/(1+B11)^5-'2. Historical Financials'!G30)/'3. Assumptions'!C28 -> 121.01787
B12: 0.11 | C12: =('5. Free Cash Flow'!D14/(1+B12)^1+'5. Free Cash Flow'!E14/(1+B12)^2+'5. Free Cash Flow'!F14/(1+B12)^3+'5. Free Cash Flow'!G14/(1+B12)^4+'5. Free Cash Flow'!H14/(1+B12)^5+'5. Free Cash Flow'!H14*(1+C$5)/(B12-C$5)/(1+B12)^5-'2. Historical Financials'!G30)/'3. Assumptions'!C28 -> 92.098564 | D12: =('5. Free Cash Flow'!D14/(1+B12)^1+'5. Free Cash Flow'!E14/(1+B12)^2+'5. Free Cash Flow'!F14/(1+B12)^3+'5. Free Cash Flow'!G14/(1+B12)^4+'5. Free Cash Flow'!H14/(1+B12)^5+'5. Free Cash Flow'!H14*(1+D$5)/(B12-D$5)/(1+B12)^5-'2. Historical Financials'!G30)/'3. Assumptions'!C28 -> 96.207578 | E12: =('5. Free Cash Flow'!D14/(1+B12)^1+'5. Free Cash Flow'!E14/(1+B12)^2+'5. Free Cash Flow'!F14/(1+B12)^3+'5. Free Cash Flow'!G14/(1+B12)^4+'5. Free Cash Flow'!H14/(1+B12)^5+'5. Free Cash Flow'!H14*(1+E$5)/(B12-E$5)/(1+B12)^5-'2. Historical Financials'!G30)/'3. Assumptions'!C28 -> 100.83022 | F12: =('5. Free Cash Flow'!D14/(1+B12)^1+'5. Free Cash Flow'!E14/(1+B12)^2+'5. Free Cash Flow'!F14/(1+B12)^3+'5. Free Cash Flow'!G14/(1+B12)^4+'5. Free Cash Flow'!H14/(1+B12)^5+'5. Free Cash Flow'!H14*(1+F$5)/(B12-F$5)/(1+B12)^5-'2. Historical Financials'!G30)/'3. Assumptions'!C28 -> 106.06921 | G12: =('5. Free Cash Flow'!D14/(1+B12)^1+'5. Free Cash Flow'!E14/(1+B12)^2+'5. Free Cash Flow'!F14/(1+B12)^3+'5. Free Cash Flow'!G14/(1+B12)^4+'5. Free Cash Flow'!H14/(1+B12)^5+'5. Free Cash Flow'!H14*(1+G$5)/(B12-G$5)/(1+B12)^5-'2. Historical Financials'!G30)/'3. Assumptions'!C28 -> 112.05663
B14: Current Price | C14: ='3. Assumptions'!C29 -> 330
B16: Yellow cell = Base case (WACC 9.5%, terminal growth 3.0%)
B18: TERMINAL VALUE: EXIT MULTIPLE METHOD
B19: Item | C19: Value | D19: Notes
B20: FY2030E EBITDA | C20: ='4. Income Statement'!H16 -> 196124.54 | D20: Final year EBITDA
B21: Exit EV/EBITDA Multiple | C21: ='3. Assumptions'!C35 -> 18 | D21: Peer median multiple
B22: Terminal Value (Exit Multiple) | C22: =C20*C21 -> 3530241.8 | D22: EBITDA x multiple
B23: PV of Terminal Value | C23: =C22/(1+'6. WACC'!J1)^5 -> 2255707.4 | D23: Discounted at WACC
B24: Enterprise Value (Exit Multiple) | C24: =C7+C23 -> 2255837.1 | D24: PV FCFF + PV TV
B25: Equity Value | C25: =C24-'2. Historical Financials'!G30 -> 2198157.1 | D25: EV - Net Debt
B26: Implied Share Price | C26: =C25/'3. Assumptions'!C28 -> 148.8258 | D26: Equity / Shares

Sheet 9. Comparables
B2: Comparable Company Analysis
B3: Trading multiples for peer group — as of October 2026
B5: COMPARABLE COMPANIES
B6: Company | C6: Ticker | D6: Price | E6: Market Cap ($B) | F6: Revenue TTM ($B) | G6: EBITDA TTM ($B) | H6: P/E (TTM) | I6: EV/EBITDA | J6: EV/Sales
B7: Apple | C7: AAPL | D7: 330 | E7: 4874 | F7: 416.2 | G7: 144.7 | H7: 38.2 | I7: 33.8 | J7: 11.6
B8: Microsoft | C8: MSFT | D8: 475 | E8: 3534 | F8: 280.2 | G8: 129 | H8: 28.5 | I8: 25.8 | J8: 12.1
B9: Alphabet | C9: GOOGL | D9: 185 | E9: 2274 | F9: 350 | G9: 120 | H9: 23.1 | I9: 18.5 | J9: 6.3
B10: Meta Platforms | C10: META | D10: 590 | E10: 1498 | F10: 149 | G10: 75 | H10: 27.8 | I10: 19.5 | J10: 9.8
B11: Samsung Electronics | C11: SSNLF | D11: 42 | E11: 280 | F11: 238 | G11: 55 | H11: 14.2 | I11: 9.8 | J11: 1.2
B12: Sony Group | C12: SONY | D12: 28 | E12: 175 | F12: 88 | G12: 15 | H12: 16.5 | I12: 11.2 | J12: 2
B14: SUMMARY STATISTICS
B15: Statistic | G15: P/E (TTM) | H15: EV/EBITDA | I15: EV/Sales
B16: Median | H16: =MEDIAN(H7:H12) -> 25.45 | I16: =MEDIAN(I7:I12) -> 19 | J16: =MEDIAN(J7:J12) -> 8.05
B17: Mean | H17: =AVERAGE(H7:H12) -> 24.716667 | I17: =AVERAGE(I7:I12) -> 19.766667 | J17: =AVERAGE(J7:J12) -> 7.1666667
B18: Min | H18: =MIN(H7:H12) -> 14.2 | I18: =MIN(I7:I12) -> 9.8 | J18: =MIN(J7:J12) -> 1.2
B19: Max | H19: =MAX(H7:H12) -> 38.2 | I19: =MAX(I7:I12) -> 33.8 | J19: =MAX(J7:J12) -> 12.1
B22: IMPLIED VALUATION FOR AAPL (USING PEER MEDIAN MULTIPLES)
B23: Method | C23: AAPL Metric | D23: Peer Median | E23: Implied EV ($B) | F23: Implied Price
B24: EV/EBITDA | C24: 144.7 | D24: =I16 -> 19 | E24: =C24*D24 -> 2749.3 | F24: =(E24*1000-'2. Historical Financials'!G30)/'3. Assumptions'!C28 -> 182.23561
B25: EV/Sales | C25: 416.2 | D25: =J16 -> 8.05 | E25: =C25*D25 -> 3350.41 | F25: =(E25*1000-'2. Historical Financials'!G30)/'3. Assumptions'!C28 -> 222.93365
B26: P/E (TTM) | C26: 112 | D26: =H16 -> 25.45 | E26: =C26*D26 -> 2850.4 | F26: =(E26*1000-'2. Historical Financials'!G30)/'3. Assumptions'!C28 -> 189.08057
B28: Source: Public market data as of October 2026. Peer multiples are illustrative.
